{
  "rules": [
    {
      "rulePriority": 1,
      "description": "Keep last 30 images",
      "selection": {
        "tagStatus": "tagged",
        "tagPrefixList": [
          "v"
        ],
        "countType": "imageCountMoreThan",
        "countNumber": 30
      },
      "action": {
        "type": "expire"
      }
    },
    {
      "rulePriority": 2,
      "description": "Expire images older than 7 days",
      "selection": {
        "tagStatus": "untagged",
        "countType": "sinceImagePushed",
        "countUnit": "days",
        "countNumber": 7
      },
      "action": {
        "type": "expire"
      }
    }
  ]
}
